{"type":"PR","pr":{"number":95,"head":"2d53951ab5e0b5a4dfcf8dc5686a9a068b537597"},"user":"silvia.vernotico","status":"pending_publish","branch":"cms/2018-04-15-horace-walpole-la-serendipity-e-cercare-un-ago-in-un-pagliaio-e-trovarci-la-figlia-del-contadino","collection":"pharmaquotes","title":"JULIUS H.COMROE - “La Serendipity è cercare un ago in un pagliaio e trovarci la figlia del contadino”","description":"Il termine Serendipity deriva da Serendip, l’antico nome persiano dello Sri Lanka e indica lo scoprire una cosa non cercata mentre se ne sta cercando un’altra. Il neologismo fu coniato nel XVIII secolo dallo scrittore Horace Walpole che lo usò per la prima volta in una lettera a un suo amico, ispirato dalla fiaba persiana dei “Tre principi di Serendippo” scritta da Cristoforo Armeno. Non è pura e mera casualità, come potrebbe portarci a pensare di prima impatto ma racchiude in sé intuizione, fantasia e acume pratico. La serendipity racchiude in sè il tipico elemento della ricerca scientifica, quando spesso scoperte importanti avvengono mentre si stava ricercando altro. ","objects":{"entry":{"path":"site/content/pharmaquotes/2018-04-15-horace-walpole-la-serendipity-e-cercare-un-ago-in-un-pagliaio-e-trovarci-la-figlia-del-contadino.md","sha":"d5b5141bec428d42811a853577d48abf003a14af"},"files":[{"path":"/site/static/img/horace.png","sha":"6a6a89235e08467369017c5501be937d81a68502"}]},"timeStamp":"2018-12-15T10:06:17.508Z"}